PyQtPath/__init__.py
PyQtPath/path_chain_pyqt6.py
PyQtPath/path_str_pyqt6.py
PyQtPath/types.py
pyqtpath-0.3.3.dist-info/licenses/LICENSE
pyqtpath-0.3.3.dist-info/METADATA
pyqtpath-0.3.3.dist-info/WHEEL
pyqtpath-0.3.3.dist-info/top_level.txt
pyqtpath-0.3.3.dist-info/RECORD
