Metadata-Version: 2.4
Name: PyQtPath
Version: 0.3.3
Summary: Retrieve nested PyQt widgets by path
Author-email: Alexey Yablokov <alex_ya@mailbox.org>
License-Expression: GPL-3.0-or-later
Project-URL: Homepage, https://github.com/Aleks-Ya/PyQtPath
Project-URL: Issues, https://github.com/Aleks-Ya/PyQtPath/issues
Classifier: Programming Language :: Python :: 3
Classifier: Operating System :: OS Independent
Requires-Python: >=3.9
License-File: LICENSE
Dynamic: license-file
